<!--Copyright 2015 MLB Advanced Media, L.P.  Use of any content on this page acknowledges agreement to the terms posted here http://gdx.mlb.com/components/copyright.txt--><Player team="tba" id="502042" pos="P" type="pitcher" first_name="Chris" last_name="Archer" jersey_number="22" height="6-3" weight="190" bats="R" throws="R" dob="09/26/1988"><season avg=".198" ab="177" h="35" rbi="15" hr="3" bb="15" so="58" w="3" l="4" sv="0" ip="48.2" whip="1.03" era="2.59"/><career avg=".230" ab="1486" h="342" rbi="162" hr="33" bb="138" so="368" w="23" l="23" sv="0" ip="401.1" whip="1.20" era="3.30"/><Month des="May" avg=".266" ab="64" h="17" rbi="11" hr="1" bb="9" so="21" ip="15.2" whip="1.66" era="6.32"/><Team des="Home" avg=".239" ab="134" h="32" rbi="15" hr="3" bb="12" so="42" ip="34.0" whip="1.29" era="3.71"/><Empty avg=".187" ab="123" h="23" rbi="2" hr="2" bb="5" so="31" ip="33.1" whip="0.84" era="0.54"/><Men_On avg=".222" ab="54" h="12" rbi="13" hr="1" bb="10" so="27" ip="14.2" whip="1.50" era="7.36"/><RISP avg=".184" ab="38" h="7" rbi="13" hr="1" bb="4" so="20" ip="10.1" whip="1.06" era="10.45"/><Loaded avg=".500" ab="6" h="3" rbi="6" hr="0" bb="2" so="1" ip="1.0" whip="5.00" era="54.00"/><vs_LHB avg=".211" ab="90" h="19" rbi="8" hr="1" bb="5" so="30" ip="23.2" whip="1.01" era="2.66"/><vs_RHB avg=".184" ab="87" h="16" rbi="7" hr="2" bb="10" so="28" ip="24.1" whip="1.07" era="2.59"/><vs_B des="Teixeira" avg=".000" ab="0" h="0" rbi="0" hr="0" bb="0" so="0" ip="0.0" whip="-" era="-"/><vs_B5 des="Teixeira" avg=".167" ab="6" h="1" rbi="0" hr="0" bb="0" so="1" ip="1.2" whip="0.60" era="0.00"/><Pitch out="FT"/></Player>