<!--Copyright 2015 MLB Advanced Media, L.P.  Use of any content on this page acknowledges agreement to the terms posted here http://gdx.mlb.com/components/copyright.txt--><inning num="2" away_team="tor" home_team="bal" next="Y"><top><atbat num="7" b="0" s="0" o="1" start_tfs="231756" start_tfs_zulu="2015-05-12T23:17:56Z" batter="429665" stand="R" b_height="6-1" pitcher="501957" p_throws="R" des="Edwin Encarnacion grounds out, third baseman Manny Machado to first baseman Chris Davis.  " des_es="Edwin Encarnacion batea rodado de out, tercera base Manny Machado a primera base Chris Davis.  " event_num="42" event="Groundout" event_es="Roletazo de Out"  play_guid="a9749095-73c1-45c5-b3b6-fc55a4f2e5de" home_team_runs="0" away_team_runs="0"><pitch des="In play, out(s)" des_es="En juego, out(s)" id="40" type="X" tfs="231823" tfs_zulu="2015-05-12T23:18:23Z" x="96.19" y="156.81" event_num="40" sv_id="150512_191856" play_guid="a9749095-73c1-45c5-b3b6-fc55a4f2e5de" start_speed="89.2" end_speed="82.4" sz_top="3.45" sz_bot="1.56" pfx_x="-0.52" pfx_z="11.75" px="0.546" pz="3.036" x0="-2.311" y0="50.0" z0="6.73" vx0="7.54" vy0="-130.439" vz0="-7.229" ax="-0.896" ay="26.884" az="-11.813" break_y="23.8" break_angle="-2.6" break_length="3.1" pitch_type="FF" type_confidence=".894" zone="3" nasty="63" spin_dir="182.518" spin_rate="2266.804"  cc="" mt=""/></atbat><atbat num="8" b="2" s="0" o="2" start_tfs="231833" start_tfs_zulu="2015-05-12T23:18:33Z" batter="431145" stand="R" b_height="5-10" pitcher="501957" p_throws="R" des="Russell Martin flies out to right fielder Delmon Young.  " des_es="Russell Martin batea elevado de out a jardinero derecho Delmon Young.  " event_num="48" event="Flyout" event_es="Elevado de Out"  play_guid="fd11363a-848b-4414-a6d3-2bdfc9b8583c" home_team_runs="0" away_team_runs="0"><pitch des="Ball" des_es="Bola mala" id="44" type="B" tfs="231901" tfs_zulu="2015-05-12T23:19:01Z" x="89.4" y="178.89" event_num="44" sv_id="150512_191939" play_guid="66d27290-38b8-4884-b8e1-12223f1ebb23" start_speed="90.0" end_speed="83.9" sz_top="3.43" sz_bot="1.56" pfx_x="-6.25" pfx_z="10.7" px="0.724" pz="2.218" x0="-2.315" y0="50.0" z0="6.687" vx0="10.046" vy0="-131.335" vz0="-9.135" ax="-11.065" ay="24.105" az="-13.15" break_y="23.9" break_angle="32.2" break_length="4.0" pitch_type="FF" type_confidence=".843" zone="14" nasty="65" spin_dir="210.182" spin_rate="2431.084"  cc="" mt=""/><pitch des="Ball" des_es="Bola mala" id="45" type="B" tfs="231916" tfs_zulu="2015-05-12T23:19:16Z" x="82.05" y="138.07" event_num="45" sv_id="150512_191953" play_guid="1b71387f-9fe8-4b8f-b79f-3f8d2c08bda4" start_speed="90.1" end_speed="82.8" sz_top="3.46" sz_bot="1.6" pfx_x="-3.38" pfx_z="11.41" px="0.917" pz="3.73" x0="-2.294" y0="50.0" z0="6.731" vx0="9.491" vy0="-131.753" vz0="-5.478" ax="-5.938" ay="28.352" az="-12.079" break_y="23.8" break_angle="16.6" break_length="3.2" pitch_type="FF" type_confidence=".905" zone="12" nasty="68" spin_dir="196.461" spin_rate="2307.321"  cc="" mt=""/><pitch des="In play, out(s)" des_es="En juego, out(s)" id="46" type="X" tfs="231936" tfs_zulu="2015-05-12T23:19:36Z" x="123.02" y="170.9" event_num="46" sv_id="150512_192008" play_guid="fd11363a-848b-4414-a6d3-2bdfc9b8583c" start_speed="90.3" end_speed="83.1" sz_top="3.33" sz_bot="1.52" pfx_x="-2.94" pfx_z="11.09" px="-0.158" pz="2.514" x0="-2.459" y0="50.0" z0="6.604" vx0="6.982" vy0="-131.93" vz0="-8.232" ax="-5.174" ay="28.368" az="-12.574" break_y="23.8" break_angle="14.6" break_length="3.4" pitch_type="FF" type_confidence=".931" zone="5" nasty="26" spin_dir="194.786" spin_rate="2229.168"  cc="" mt=""/></atbat><atbat num="9" b="1" s="0" o="2" start_tfs="231946" start_tfs_zulu="2015-05-12T23:19:46Z" batter="499624" stand="R" b_height="6-4" pitcher="501957" p_throws="R" des="Chris Colabello singles on a ground ball to shortstop J.   Hardy.  " des_es="Chris Colabello pega sencillo con rodado a campo corto J.   Hardy.  " event_num="53" event="Single" event_es="Sencillo"  play_guid="59835e09-a847-4f47-a4aa-ad8b56f8fbdb" home_team_runs="0" away_team_runs="0"><pitch des="Ball" des_es="Bola mala" id="50" type="B" tfs="232016" tfs_zulu="2015-05-12T23:20:16Z" x="150.09" y="136.1" event_num="50" sv_id="150512_192053" play_guid="c57f4d83-5cd2-4cb1-893f-97e74e4ee2ce" start_speed="91.4" end_speed="84.2" sz_top="3.64" sz_bot="1.74" pfx_x="-3.22" pfx_z="9.92" px="-0.868" pz="3.803" x0="-2.416" y0="50.0" z0="6.792" vx0="5.194" vy0="-133.834" vz0="-5.229" ax="-5.835" ay="28.786" az="-14.106" break_y="23.8" break_angle="17.3" break_length="3.6" pitch_type="FF" type_confidence=".913" zone="11" nasty="85" spin_dir="197.896" spin_rate="2058.203"  cc="" mt=""/><pitch des="In play, no out" des_es="En juego, no out" id="51" type="X" tfs="232041" tfs_zulu="2015-05-12T23:20:41Z" x="96.04" y="180.3" event_num="51" sv_id="150512_192112" play_guid="59835e09-a847-4f47-a4aa-ad8b56f8fbdb" start_speed="89.6" end_speed="82.7" sz_top="3.57" sz_bot="1.6" pfx_x="-2.99" pfx_z="11.07" px="0.55" pz="2.166" x0="-2.287" y0="50.0" z0="6.634" vx0="8.342" vy0="-130.896" vz0="-9.066" ax="-5.198" ay="27.244" az="-12.864" break_y="23.8" break_angle="13.5" break_length="3.5" pitch_type="FF" type_confidence=".933" zone="9" nasty="45" spin_dir="195.065" spin_rate="2216.404"  cc="" mt=""/><runner id="499624" start="" end="1B" event="Single" event_num="53"/></atbat><atbat num="10" b="0" s="0" o="3" start_tfs="232055" start_tfs_zulu="2015-05-12T23:20:55Z" batter="607680" stand="R" b_height="6-0" pitcher="501957" p_throws="R" des="Kevin Pillar lines out to right fielder Delmon Young.  " des_es="Kevin Pillar batea l&#237;nea de out a jardinero derecho Delmon Young.  " event_num="57" event="Lineout" event_es="Línea de Out"  play_guid="919bf32b-279c-4481-a271-9b36654fe79f" home_team_runs="0" away_team_runs="0"><pitch des="In play, out(s)" des_es="En juego, out(s)" id="55" type="X" tfs="232120" tfs_zulu="2015-05-12T23:21:20Z" x="138.46" y="175.82" event_num="55" on_1b="499624" sv_id="150512_192153" play_guid="919bf32b-279c-4481-a271-9b36654fe79f" start_speed="90.1" end_speed="82.8" sz_top="3.42" sz_bot="1.55" pfx_x="-3.68" pfx_z="10.65" px="-0.563" pz="2.332" x0="-2.374" y0="50.0" z0="6.595" vx0="5.944" vy0="-131.759" vz0="-8.482" ax="-6.443" ay="28.971" az="-13.451" break_y="23.8" break_angle="18.8" break_length="3.7" pitch_type="FF" type_confidence=".928" zone="4" nasty="57" spin_dir="198.988" spin_rate="2180.218"  cc="" mt=""/><runner id="499624" start="1B" end="" event="Lineout" event_num="57"/></atbat></top><bottom><atbat num="11" b="1" s="1" o="1" start_tfs="232316" start_tfs_zulu="2015-05-12T23:23:16Z" batter="430321" stand="R" b_height="6-3" pitcher="279824" p_throws="L" des="Delmon Young grounds out, third baseman Josh Donaldson to first baseman Edwin Encarnacion.  " des_es="Delmon Young batea rodado de out, tercera base Josh Donaldson a primera base Edwin Encarnacion.  " event_num="65" event="Groundout" event_es="Roletazo de Out"  play_guid="7c980639-d167-4bbf-afd0-0a346266fb53" home_team_runs="0" away_team_runs="0"><pitch des="Called Strike" des_es="Strike cantado" id="61" type="S" tfs="232324" tfs_zulu="2015-05-12T23:23:24Z" x="86.35" y="178.68" event_num="61" sv_id="150512_192401" play_guid="e1b3f505-b2bd-4169-9e8e-1495558d9731" start_speed="78.8" end_speed="72.8" sz_top="3.71" sz_bot="1.74" pfx_x="8.63" pfx_z="6.3" px="0.804" pz="2.226" x0="1.358" y0="50.0" z0="6.196" vx0="-3.815" vy0="-115.497" vz0="-3.862" ax="11.626" ay="22.0" az="-23.609" break_y="23.8" break_angle="-24.2" break_length="8.0" pitch_type="CH" type_confidence=".905" zone="14" nasty="75" spin_dir="126.380" spin_rate="1813.880"  cc="" mt=""/><pitch des="Ball" des_es="Bola mala" id="62" type="B" tfs="232335" tfs_zulu="2015-05-12T23:23:35Z" x="171.13" y="146.33" event_num="62" sv_id="150512_192411" play_guid="5ff6bf3e-516d-42c6-b293-232ebe3543a1" start_speed="81.2" end_speed="75.3" sz_top="3.71" sz_bot="1.74" pfx_x="1.96" pfx_z="8.47" px="-1.42" pz="3.424" x0="1.023" y0="50.0" z0="6.302" vx0="-6.351" vy0="-118.828" vz0="-2.543" ax="2.828" ay="21.248" az="-19.898" break_y="23.8" break_angle="-4.9" break_length="5.7" pitch_type="FF" type_confidence=".723" zone="11" nasty="33" spin_dir="167.029" spin_rate="1538.044"  cc="" mt=""/><pitch des="In play, out(s)" des_es="En juego, out(s)" id="63" type="X" tfs="232349" tfs_zulu="2015-05-12T23:23:49Z" x="107.93" y="191.58" event_num="63" sv_id="150512_192422" play_guid="7c980639-d167-4bbf-afd0-0a346266fb53" start_speed="80.0" end_speed="73.9" sz_top="3.58" sz_bot="1.67" pfx_x="10.09" pfx_z="6.68" px="0.238" pz="1.748" x0="1.239" y0="50.0" z0="6.071" vx0="-5.339" vy0="-117.155" vz0="-5.039" ax="13.987" ay="22.761" az="-22.851" break_y="23.8" break_angle="-28.7" break_length="7.9" pitch_type="CH" type_confidence=".832" zone="9" nasty="40" spin_dir="123.686" spin_rate="2081.577"  cc="" mt=""/></atbat><atbat num="12" b="0" s="0" o="2" start_tfs="232401" start_tfs_zulu="2015-05-12T23:24:01Z" batter="448801" stand="L" b_height="6-3" pitcher="279824" p_throws="L" des="Chris Davis flies out to right fielder Chris Colabello.  " des_es="Chris Davis batea elevado de out a jardinero derecho Chris Colabello.  " event_num="69" event="Flyout" event_es="Elevado de Out"  play_guid="6af9f1e6-3c43-4789-aa02-0d8ae5918ed9" home_team_runs="0" away_team_runs="0"><pitch des="In play, out(s)" des_es="En juego, out(s)" id="67" type="X" tfs="232423" tfs_zulu="2015-05-12T23:24:23Z" x="92.83" y="173.66" event_num="67" sv_id="150512_192456" play_guid="6af9f1e6-3c43-4789-aa02-0d8ae5918ed9" start_speed="81.1" end_speed="75.0" sz_top="3.66" sz_bot="1.67" pfx_x="7.61" pfx_z="7.55" px="0.634" pz="2.412" x0="1.324" y0="50.0" z0="6.216" vx0="-3.941" vy0="-118.768" vz0="-4.386" ax="10.889" ay="22.413" az="-21.294" break_y="23.8" break_angle="-24.8" break_length="6.9" pitch_type="FT" type_confidence=".889" zone="6" nasty="54" spin_dir="134.977" spin_rate="1880.296"  cc="" mt=""/></atbat><atbat num="13" b="0" s="1" o="3" start_tfs="232436" start_tfs_zulu="2015-05-12T23:24:36Z" batter="456665" stand="R" b_height="5-11" pitcher="279824" p_throws="L" des="Steve Pearce lines out to center fielder Kevin Pillar.  " des_es="Steve Pearce batea l&#237;nea de out a jardinero central Kevin Pillar.  " event_num="74" event="Lineout" event_es="Línea de Out"  play_guid="e9b78587-9ec5-491e-b208-7866bff4d573" home_team_runs="0" away_team_runs="0"><pitch des="Called Strike" des_es="Strike cantado" id="71" type="S" tfs="232452" tfs_zulu="2015-05-12T23:24:52Z" x="143" y="179.57" event_num="71" sv_id="150512_192529" play_guid="c8b9babc-5b5f-4aa4-890b-a2ba7ac99615" start_speed="82.2" end_speed="76.0" sz_top="3.68" sz_bot="1.53" pfx_x="1.13" pfx_z="7.48" px="-0.682" pz="2.193" x0="1.116" y0="50.0" z0="6.176" vx0="-4.622" vy0="-120.408" vz0="-5.023" ax="1.653" ay="23.432" az="-21.127" break_y="23.8" break_angle="-2.1" break_length="6.1" pitch_type="FF" type_confidence=".790" zone="7" nasty="65" spin_dir="171.492" spin_rate="1345.859"  cc="" mt=""/><pitch des="In play, out(s)" des_es="En juego, out(s)" id="72" type="X" tfs="232504" tfs_zulu="2015-05-12T23:25:04Z" x="113.42" y="173.17" event_num="72" sv_id="150512_192539" play_guid="e9b78587-9ec5-491e-b208-7866bff4d573" start_speed="80.7" end_speed="74.8" sz_top="3.46" sz_bot="1.53" pfx_x="4.88" pfx_z="5.59" px="0.094" pz="2.43" x0="1.271" y0="50.0" z0="6.226" vx0="-4.234" vy0="-118.217" vz0="-3.697" ax="6.931" ay="21.926" az="-24.166" break_y="23.8" break_angle="-14.0" break_length="7.3" pitch_type="FT" type_confidence=".918" zone="5" nasty="29" spin_dir="139.125" spin_rate="1299.734"  cc="" mt=""/></atbat></bottom></inning>