<!--Copyright 2015 MLB Advanced Media, L.P.  Use of any content on this page acknowledges agreement to the terms posted here http://gdx.mlb.com/components/copyright.txt--><Player team="tex" id="527048" pos="P" type="pitcher" first_name="Martin" last_name="Perez" jersey_number="33" height="6-0" weight="195" bats="L" throws="L" dob="04/04/1991"><season avg=".000" ab="0" h="0" rbi="0" hr="0" bb="0" so="0" w="0" l="0" sv="0" ip="0.0" whip="-" era="-"/><career avg=".273" ab="828" h="226" rbi="96" hr="21" bb="71" so="144" w="15" l="13" sv="0" ip="213.2" whip="1.39" era="4.13"/><Month des="May" avg=".000" ab="0" h="0" rbi="0" hr="0" bb="0" so="0" ip="0.0" whip="-" era="-"/><Team des="Home" avg=".000" ab="0" h="0" rbi="0" hr="0" bb="0" so="0" ip="0.0" whip="-" era="-"/><Empty avg=".000" ab="0" h="0" rbi="0" hr="0" bb="0" so="0" ip="0.0" whip="-" era="-"/><Men_On avg=".000" ab="0" h="0" rbi="0" hr="0" bb="0" so="0" ip="0.0" whip="-" era="-"/><RISP avg=".000" ab="0" h="0" rbi="0" hr="0" bb="0" so="0" ip="0.0" whip="-" era="-"/><Loaded avg=".000" ab="0" h="0" rbi="0" hr="0" bb="0" so="0" ip="0.0" whip="-" era="-"/><vs_LHB avg=".000" ab="0" h="0" rbi="0" hr="0" bb="0" so="0" ip="0.0" whip="-" era="-"/><vs_RHB avg=".000" ab="0" h="0" rbi="0" hr="0" bb="0" so="0" ip="0.0" whip="-" era="-"/><vs_B des="Dyson, J" avg=".000" ab="0" h="0" rbi="0" hr="0" bb="0" so="0" ip="0.0" whip="-" era="-"/><vs_B5 des="Dyson, J" avg=".000" ab="0" h="0" rbi="0" hr="0" bb="0" so="0" ip="0.0" whip="-" era="-"/><Pitch out="--"/></Player>