<!--Copyright 2015 MLB Advanced Media, L.P.  Use of any content on this page acknowledges agreement to the terms posted here http://gdx.mlb.com/components/copyright.txt--><Player team="sfn" id="433586" pos="P" type="pitcher" first_name="Santiago" last_name="Casilla" jersey_number="46" height="6-0" weight="210" bats="R" throws="R" dob="07/25/1980"><season avg=".250" ab="52" h="13" rbi="3" hr="1" bb="5" so="11" w="4" l="0" sv="8" ip="14.1" whip="1.26" era="1.88"/><career avg=".231" ab="1678" h="388" rbi="165" hr="37" bb="198" so="388" w="36" l="19" sv="66" ip="453.1" whip="1.29" era="3.16"/><Month des="May" avg=".188" ab="16" h="3" rbi="0" hr="0" bb="1" so="3" ip="4.2" whip="0.86" era="0.00"/><Team des="Away" avg=".188" ab="16" h="3" rbi="1" hr="0" bb="0" so="4" ip="4.2" whip="0.64" era="1.93"/><Empty avg=".281" ab="32" h="9" rbi="1" hr="1" bb="1" so="6" ip="7.1" whip="1.36" era="1.23"/><Men_On avg=".200" ab="20" h="4" rbi="2" hr="0" bb="4" so="5" ip="7.0" whip="1.14" era="2.57"/><RISP avg=".143" ab="14" h="2" rbi="2" hr="0" bb="3" so="3" ip="5.0" whip="1.00" era="3.60"/><Loaded avg=".000" ab="1" h="0" rbi="0" hr="0" bb="0" so="1" ip="0.2" whip="0.00" era="0.00"/><vs_LHB avg=".278" ab="18" h="5" rbi="0" hr="0" bb="2" so="6" ip="5.1" whip="1.31" era="0.00"/><vs_RHB avg=".235" ab="34" h="8" rbi="3" hr="1" bb="3" so="5" ip="9.0" whip="1.22" era="3.00"/><vs_B des="Altuve" avg=".000" ab="0" h="0" rbi="0" hr="0" bb="0" so="0" ip="0.0" whip="-" era="-"/><vs_B5 des="Altuve" avg=".000" ab="4" h="0" rbi="0" hr="0" bb="0" so="1" ip="1.1" whip="0.00" era="0.00"/><Pitch out="--"/></Player>