<!--Copyright 2015 MLB Advanced Media, L.P.  Use of any content on this page acknowledges agreement to the terms posted here http://gdx.mlb.com/components/copyright.txt--><inning num="9" away_team="col" home_team="ana" next="N"><top><action b="0" s="0" o="0" des="Collin Cowgill remains in the game as the left fielder.  " des_es="Collin Cowgill permanece en el juego como el jardinero izquierdo.  " event="Defensive Switch" event_es="Cambio Defensivo" tfs="044500" tfs_zulu="2015-05-13T04:45:00Z" player="518577" pitch="4" event_num="509" home_team_runs="5" away_team_runs="2"/><action b="0" s="0" o="0" des="C.  J.   Cron remains in the game as the first baseman.  " des_es="C.  J.   Cron permanece en el juego como el primera base.  " event="Defensive Switch" event_es="Cambio Defensivo" tfs="044501" tfs_zulu="2015-05-13T04:45:01Z" player="543068" pitch="4" event_num="511" home_team_runs="5" away_team_runs="2"/><action b="0" s="0" o="0" des="Pitching Change: Huston Street replaces C.  J.   Wilson.  " des_es="Cambio de Lanzador: Huston Street reemplaza a C.  J.   Wilson.  " event="Pitching Substitution" event_es="Cambio de Lanzador" tfs="044501" tfs_zulu="2015-05-13T04:45:01Z" player="434718" pitch="4" event_num="513" home_team_runs="5" away_team_runs="2"/><atbat num="68" b="1" s="3" o="1" start_tfs="044632" start_tfs_zulu="2015-05-13T04:46:32Z" batter="571448" stand="R" b_height="6-2" pitcher="434718" p_throws="R" des="Nolan Arenado called out on strikes.  " des_es="Nolan Arenado se poncha sin tirarle.  " event_num="520" event="Strikeout" event_es="Ponche"  play_guid="00080d47-3a50-4cf5-ae6e-521449678b07" home_team_runs="5" away_team_runs="2"><pitch des="Ball" des_es="Bola mala" id="515" type="B" tfs="044649" tfs_zulu="2015-05-13T04:46:49Z" x="76.6" y="204.84" event_num="515" sv_id="150512_214607" play_guid="" start_speed="87.9" end_speed="79.4" sz_top="3.41" sz_bot="1.69" pfx_x="-10.31" pfx_z="9.13" px="1.06" pz="1.257" x0="-1.606" y0="50.0" z0="5.182" vx0="10.046" vy0="-128.324" vz0="-6.434" ax="-16.829" ay="31.781" az="-17.193" break_y="23.7" break_angle="37.6" break_length="5.9" pitch_type="SI" type_confidence=".000" zone="14" nasty="61" spin_dir="228.324" spin_rate="2547.268"  cc="" mt=""/><pitch des="Called Strike" des_es="Strike cantado" id="516" type="S" tfs="044705" tfs_zulu="2015-05-13T04:47:05Z" x="73.58" y="193.66" event_num="516" sv_id="150512_214622" play_guid="" start_speed="87.9" end_speed="79.7" sz_top="3.27" sz_bot="1.47" pfx_x="-9.51" pfx_z="9.32" px="1.139" pz="1.671" x0="-1.588" y0="50.0" z0="5.29" vx0="9.966" vy0="-128.399" vz0="-5.778" ax="-15.613" ay="30.642" az="-16.789" break_y="23.7" break_angle="36.3" break_length="5.6" pitch_type="SI" type_confidence=".000" zone="14" nasty="66" spin_dir="225.420" spin_rate="2476.686"  cc="" mt=""/><pitch des="Swinging Strike" des_es="Strike tir&#225;ndole" id="517" type="S" tfs="044733" tfs_zulu="2015-05-13T04:47:33Z" x="63.44" y="170.28" event_num="517" sv_id="150512_214641" play_guid="" start_speed="82.0" end_speed="74.9" sz_top="3.48" sz_bot="1.58" pfx_x="-0.56" pfx_z="4.06" px="1.405" pz="2.537" x0="-1.538" y0="50.0" z0="5.667" vx0="7.101" vy0="-120.003" vz0="-1.796" ax="-0.808" ay="26.321" az="-26.259" break_y="23.7" break_angle="-1.4" break_length="7.5" pitch_type="SL" type_confidence=".908" zone="12" nasty="12" spin_dir="187.777" spin_rate="721.738"  cc="" mt=""/><pitch des="Called Strike" des_es="Strike cantado" id="518" type="S" tfs="044805" tfs_zulu="2015-05-13T04:48:05Z" x="83.99" y="187.59" event_num="518" sv_id="150512_214707" play_guid="00080d47-3a50-4cf5-ae6e-521449678b07" start_speed="83.0" end_speed="76.5" sz_top="3.48" sz_bot="1.58" pfx_x="-1.72" pfx_z="2.34" px="0.866" pz="1.896" x0="-1.478" y0="50.0" z0="5.555" vx0="6.149" vy0="-121.613" vz0="-2.793" ax="-2.563" ay="25.092" az="-28.616" break_y="23.8" break_angle="2.7" break_length="8.0" pitch_type="SL" type_confidence=".905" zone="14" nasty="53" spin_dir="215.766" spin_rate="523.110"  cc="" mt=""/></atbat><atbat num="69" b="2" s="2" o="2" start_tfs="044810" start_tfs_zulu="2015-05-13T04:48:10Z" batter="408047" stand="L" b_height="6-4" pitcher="434718" p_throws="R" des="Justin Morneau flies out to center fielder Mike Trout.  " des_es="Justin Morneau batea elevado de out a jardinero central Mike Trout.  " event_num="528" event="Flyout" event_es="Elevado de Out"  play_guid="a4f45310-f0fe-4db0-921f-eb8ad415a51a" home_team_runs="5" away_team_runs="2"><pitch des="Ball" des_es="Bola mala" id="522" type="B" tfs="044827" tfs_zulu="2015-05-13T04:48:27Z" x="187.1" y="174.47" event_num="522" sv_id="150512_214742" play_guid="487229fd-972a-4baa-a207-21e4f9868893" start_speed="87.6" end_speed="79.4" sz_top="3.46" sz_bot="1.61" pfx_x="-9.57" pfx_z="9.26" px="-1.839" pz="2.382" x0="-2.053" y0="50.0" z0="5.406" vx0="3.653" vy0="-128.39" vz0="-4.232" ax="-15.656" ay="31.463" az="-16.952" break_y="23.7" break_angle="39.4" break_length="5.8" pitch_type="SI" type_confidence=".000" zone="13" nasty="35" spin_dir="225.804" spin_rate="2467.448"  cc="" mt=""/><pitch des="Swinging Strike" des_es="Strike tir&#225;ndole" id="523" type="S" tfs="044841" tfs_zulu="2015-05-13T04:48:41Z" x="168.69" y="176.92" event_num="523" sv_id="150512_214758" play_guid="28de42ac-2b72-4229-a27b-d2f3aa3122d0" start_speed="88.4" end_speed="80.1" sz_top="3.45" sz_bot="1.58" pfx_x="-8.78" pfx_z="10.9" px="-1.356" pz="2.291" x0="-1.531" y0="50.0" z0="5.658" vx0="3.328" vy0="-129.507" vz0="-5.787" ax="-14.626" ay="32.013" az="-13.945" break_y="23.7" break_angle="42.0" break_length="5.1" pitch_type="SI" type_confidence=".000" zone="13" nasty="29" spin_dir="218.741" spin_rate="2618.131"  cc="" mt=""/><pitch des="Foul Tip" des_es="Foul atr&#225;s" id="524" type="S" tfs="044901" tfs_zulu="2015-05-13T04:49:01Z" x="151.04" y="162.42" event_num="524" sv_id="150512_214816" play_guid="63a89986-9c8c-4f1c-98dc-2bebe91d6a53" start_speed="89.3" end_speed="80.8" sz_top="3.45" sz_bot="1.58" pfx_x="-8.28" pfx_z="8.13" px="-0.893" pz="2.828" x0="-1.313" y0="50.0" z0="5.85" vx0="3.817" vy0="-130.814" vz0="-4.155" ax="-14.037" ay="33.09" az="-18.321" break_y="23.7" break_angle="34.1" break_length="5.6" pitch_type="SI" type_confidence=".000" zone="11" nasty="60" spin_dir="225.377" spin_rate="2187.212"  cc="" mt=""/><pitch des="Ball" des_es="Bola mala" id="525" type="B" tfs="044922" tfs_zulu="2015-05-13T04:49:22Z" x="119.67" y="243.51" event_num="525" sv_id="150512_214840" play_guid="47ef2cf2-e0da-4035-b983-e33ddc538a5f" start_speed="80.7" end_speed="74.1" sz_top="3.37" sz_bot="1.52" pfx_x="-8.74" pfx_z="6.65" px="-0.07" pz="-0.175" x0="-1.488" y0="50.0" z0="5.346" vx0="5.911" vy0="-117.952" vz0="-7.859" ax="-12.166" ay="25.011" az="-22.852" break_y="23.8" break_angle="24.3" break_length="7.8" pitch_type="CH" type_confidence=".903" zone="13" nasty="17" spin_dir="232.539" spin_rate="1885.163"  cc="" mt=""/><pitch des="In play, out(s)" des_es="En juego, out(s)" id="526" type="X" tfs="045000" tfs_zulu="2015-05-13T04:50:00Z" x="113.76" y="185.32" event_num="526" sv_id="150512_214912" play_guid="a4f45310-f0fe-4db0-921f-eb8ad415a51a" start_speed="82.5" end_speed="76.1" sz_top="3.45" sz_bot="1.58" pfx_x="1.05" pfx_z="2.99" px="0.085" pz="1.98" x0="-1.412" y0="50.0" z0="5.663" vx0="3.242" vy0="-120.909" vz0="-2.965" ax="1.551" ay="24.55" az="-27.691" break_y="23.8" break_angle="-4.3" break_length="7.8" pitch_type="SL" type_confidence=".900" zone="8" nasty="27" spin_dir="160.917" spin_rate="569.197"  cc="" mt=""/></atbat><atbat num="70" b="2" s="3" o="3" start_tfs="045008" start_tfs_zulu="2015-05-13T04:50:08Z" batter="501647" stand="R" b_height="5-11" pitcher="434718" p_throws="R" des="Wilin Rosario strikes out swinging.  " des_es="Wilin Rosario se poncha tir&#225;ndole.  " event_num="536" event="Strikeout" event_es="Ponche"  play_guid="60b3ae67-3164-44b2-98d4-1259086a250b" home_team_runs="5" away_team_runs="2"><pitch des="Called Strike" des_es="Strike cantado" id="530" type="S" tfs="045037" tfs_zulu="2015-05-13T04:50:37Z" x="94.32" y="194.31" event_num="530" sv_id="150512_214955" play_guid="b6ffb6f9-201c-43bf-9567-bf1f58d47a71" start_speed="88.5" end_speed="80.7" sz_top="3.49" sz_bot="1.69" pfx_x="-7.77" pfx_z="11.52" px="0.595" pz="1.647" x0="-1.253" y0="50.0" z0="5.624" vx0="7.26" vy0="-129.333" vz0="-7.596" ax="-13.035" ay="29.545" az="-12.793" break_y="23.7" break_angle="38.2" break_length="4.5" pitch_type="SI" type_confidence=".000" zone="14" nasty="70" spin_dir="213.922" spin_rate="2620.016"  cc="" mt=""/><pitch des="Foul" des_es="Foul" id="531" type="S" tfs="045055" tfs_zulu="2015-05-13T04:50:55Z" x="124.2" y="171.12" event_num="531" sv_id="150512_215013" play_guid="39e91c5c-14c5-4579-8721-30809923fe3a" start_speed="81.6" end_speed="74.9" sz_top="3.46" sz_bot="1.65" pfx_x="0.98" pfx_z="1.91" px="-0.189" pz="2.506" x0="-1.45" y0="50.0" z0="5.846" vx0="2.667" vy0="-119.667" vz0="-1.611" ax="1.41" ay="25.406" az="-29.366" break_y="23.8" break_angle="-3.7" break_length="8.4" pitch_type="SL" type_confidence=".901" zone="5" nasty="19" spin_dir="153.338" spin_rate="380.936"  cc="" mt=""/><pitch des="Ball" des_es="Bola mala" id="532" type="B" tfs="045126" tfs_zulu="2015-05-13T04:51:26Z" x="47.82" y="235.24" event_num="532" sv_id="150512_215045" play_guid="0844a25e-5e5f-458e-884f-4e7b105287f3" start_speed="82.0" end_speed="76.7" sz_top="3.54" sz_bot="1.56" pfx_x="-2.84" pfx_z="2.07" px="1.815" pz="0.131" x0="-1.554" y0="50.0" z0="5.381" vx0="8.868" vy0="-119.796" vz0="-6.325" ax="-4.162" ay="21.622" az="-29.072" break_y="23.9" break_angle="5.3" break_length="8.4" pitch_type="SL" type_confidence=".902" zone="14" nasty="16" spin_dir="233.302" spin_rate="628.632"  cc="" mt=""/><pitch des="Ball" des_es="Bola mala" id="533" type="B" tfs="045207" tfs_zulu="2015-05-13T04:52:07Z" x="68.55" y="230.25" event_num="533" sv_id="150512_215125" play_guid="5b495eac-da91-4918-864b-0947d56d7266" start_speed="80.0" end_speed="73.5" sz_top="3.41" sz_bot="1.56" pfx_x="-1.56" pfx_z="2.87" px="1.271" pz="0.316" x0="-1.546" y0="50.0" z0="5.419" vx0="6.932" vy0="-117.016" vz0="-5.586" ax="-2.13" ay="24.991" az="-28.174" break_y="23.8" break_angle="1.6" break_length="8.7" pitch_type="SL" type_confidence=".903" zone="14" nasty="40" spin_dir="208.034" spin_rate="561.855"  cc="" mt=""/><pitch des="Swinging Strike" des_es="Strike tir&#225;ndole" id="534" type="S" tfs="045242" tfs_zulu="2015-05-13T04:52:42Z" x="103.28" y="194.37" event_num="534" sv_id="150512_215155" play_guid="60b3ae67-3164-44b2-98d4-1259086a250b" start_speed="80.9" end_speed="74.1" sz_top="3.46" sz_bot="1.65" pfx_x="-1.47" pfx_z="1.68" px="0.36" pz="1.645" x0="-1.571" y0="50.0" z0="5.606" vx0="4.933" vy0="-118.509" vz0="-2.814" ax="-2.06" ay="25.766" az="-29.749" break_y="23.8" break_angle="2.1" break_length="8.8" pitch_type="SL" type_confidence=".907" zone="14" nasty="41" spin_dir="220.346" spin_rate="389.522"  cc="" mt=""/></atbat></top></inning>