<!--Copyright 2015 MLB Advanced Media, L.P.  Use of any content on this page acknowledges agreement to the terms posted here http://gdx.mlb.com/components/copyright.txt--><Player team="cin" id="488674" pos="P" type="pitcher" first_name="Burke" last_name="Badenhop" jersey_number="25" height="6-5" weight="210" bats="R" throws="R" dob="02/08/1983"><season avg=".381" ab="42" h="16" rbi="12" hr="2" bb="3" so="5" w="0" l="1" sv="0" ip="9.2" whip="1.97" era="11.17"/><career avg=".267" ab="1739" h="464" rbi="202" hr="33" bb="136" so="319" w="18" l="24" sv="4" ip="455.2" whip="1.32" era="3.87"/><Month des="May" avg=".000" ab="7" h="0" rbi="0" hr="0" bb="0" so="1" ip="2.2" whip="0.00" era="0.00"/><Team des="Home" avg=".522" ab="23" h="12" rbi="10" hr="0" bb="3" so="2" ip="4.0" whip="3.75" era="22.50"/><Empty avg=".222" ab="18" h="4" rbi="1" hr="1" bb="2" so="4" ip="4.1" whip="1.38" era="2.08"/><Men_On avg=".500" ab="24" h="12" rbi="11" hr="1" bb="1" so="1" ip="5.1" whip="2.44" era="18.56"/><RISP avg=".563" ab="16" h="9" rbi="11" hr="1" bb="1" so="1" ip="2.2" whip="3.75" era="37.13"/><Loaded avg=".667" ab="6" h="4" rbi="7" hr="1" bb="0" so="1" ip="1.0" whip="4.00" era="63.00"/><vs_LHB avg=".333" ab="18" h="6" rbi="2" hr="1" bb="1" so="3" ip="4.2" whip="1.50" era="3.86"/><vs_RHB avg=".417" ab="24" h="10" rbi="10" hr="1" bb="2" so="2" ip="5.0" whip="2.40" era="18.00"/><vs_B des="Pierzynski" avg=".000" ab="0" h="0" rbi="0" hr="0" bb="0" so="0" ip="0.0" whip="-" era="-"/><vs_B5 des="Pierzynski" avg=".000" ab="1" h="0" rbi="0" hr="0" bb="0" so="0" ip="0.1" whip="0.00" era="0.00"/><Pitch out="--"/></Player>