<!--Copyright 2015 MLB Advanced Media, L.P.  Use of any content on this page acknowledges agreement to the terms posted here http://gdx.mlb.com/components/copyright.txt--><Player team="cin" id="571561" pos="P" type="pitcher" first_name="Tony" last_name="Cingrani" jersey_number="52" height="6-4" weight="210" bats="L" throws="L" dob="07/05/1989"><season avg=".108" ab="37" h="4" rbi="3" hr="0" bb="9" so="13" w="0" l="0" sv="0" ip="12.0" whip="1.08" era="2.25"/><career avg=".214" ab="664" h="142" rbi="69" hr="27" bb="89" so="203" w="9" l="12" sv="0" ip="185.0" whip="1.25" era="3.41"/><Month des="May" avg=".000" ab="13" h="0" rbi="1" hr="0" bb="3" so="6" ip="4.2" whip="0.64" era="1.93"/><Team des="Home" avg=".048" ab="21" h="1" rbi="1" hr="0" bb="4" so="9" ip="7.0" whip="0.71" era="1.29"/><Empty avg=".158" ab="19" h="3" rbi="0" hr="0" bb="5" so="7" ip="5.1" whip="1.50" era="0.00"/><Men_On avg=".056" ab="18" h="1" rbi="3" hr="0" bb="4" so="6" ip="6.2" whip="0.75" era="4.05"/><RISP avg=".091" ab="11" h="1" rbi="3" hr="0" bb="2" so="3" ip="4.0" whip="0.75" era="6.75"/><Loaded avg=".000" ab="1" h="0" rbi="0" hr="0" bb="0" so="1" ip="0.1" whip="0.00" era="0.00"/><vs_LHB avg=".133" ab="15" h="2" rbi="1" hr="0" bb="3" so="6" ip="4.1" whip="1.15" era="2.08"/><vs_RHB avg=".091" ab="22" h="2" rbi="2" hr="0" bb="6" so="7" ip="7.2" whip="1.04" era="2.35"/><vs_B des="Pierzynski" avg=".000" ab="1" h="0" rbi="0" hr="0" bb="0" so="0" ip="0.1" whip="0.00" era="0.00"/><vs_B5 des="Pierzynski" avg=".000" ab="3" h="0" rbi="0" hr="0" bb="0" so="0" ip="1.0" whip="0.00" era="0.00"/><Pitch out="--"/></Player>